metlibvi/__init__.py
metlibvi/callbacks/__init__.py
metlibvi/callbacks/met_callbacks.py
metlibvi/datasets/__init__.py
metlibvi/datasets/datasets.py
metlibvi/mcmc/__init__.py
metlibvi/mcmc/kernels.py
metlibvi/mcmc/utils.py
metlibvi/plotting/__init__.py
metlibvi/plotting/debug_plots.py
metlibvi/plotting/plot_functions.py
metlibvi/targets/__init__.py
metlibvi/targets/targets.py
metlibvi/train_utils/__init__.py
metlibvi/train_utils/forward_steps.py
metlibvi/train_utils/losses.py
metlibvi/trainers/__init__.py
metlibvi/trainers/pytorch_trainers.py
metlibvi/vi/__init__.py
metlibvi/vi/normflow.py
tests/__init__.py
tests/conftest.py
tests/test_kernels.py
tests/test_mh.py
tests/test_vi.py
metlibvi-0.1.10.dist-info/LICENSE
metlibvi-0.1.10.dist-info/METADATA
metlibvi-0.1.10.dist-info/WHEEL
metlibvi-0.1.10.dist-info/top_level.txt
metlibvi-0.1.10.dist-info/RECORD
