Metadata-Version: 2.1
Name: metlibvi
Version: 0.1.10
Summary: Library for metropolized variational inference.
Home-page: https://github.com/nkotelevskii/metlib
Author: Nikita Kotelevskii, Achille Thin
Author-email: Nikita.Kotelevskii@skoltech.ru
License: MIT
Platform: UNKNOWN
